mapchete_xarray/__init__.py
mapchete_xarray/_input.py
mapchete_xarray/_output.py
mapchete_xarray/processes/__init__.py
mapchete_xarray/processes/convert_to_xarray.py
mapchete_xarray-2023.6.0.dist-info/LICENSE
mapchete_xarray-2023.6.0.dist-info/METADATA
mapchete_xarray-2023.6.0.dist-info/WHEEL
mapchete_xarray-2023.6.0.dist-info/entry_points.txt
mapchete_xarray-2023.6.0.dist-info/top_level.txt
mapchete_xarray-2023.6.0.dist-info/RECORD
