Metadata-Version: 2.1
Name: mapchete-xarray
Version: 2023.6.0
Summary: Mapchete xarray output driver
Home-page: https://github.com/ungarj/mapchete_xarray
Author: Joachim Ungar
Author-email: joachim.ungar@gmail.com
License: MIT
Classifier: Development Status :: 3 - Alpha
Classifier: Intended Audience :: Developers
Classifier: Topic :: Scientific/Engineering :: GIS
Classifier: License :: OSI Approved :: MIT License
Classifier: Programming Language :: Python :: 3.8
Classifier: Programming Language :: Python :: 3.9
Classifier: Programming Language :: Python :: 3.10
License-File: LICENSE
Requires-Dist: croniter
Requires-Dist: dask
Requires-Dist: mapchete[s3] (>=2023.6.3)
Requires-Dist: python-dateutil
Requires-Dist: xarray
Requires-Dist: zarr
